setup.py
zssget/__init__.py
zssget/__main__.py
zssget/common.py
zssget.egg-info/PKG-INFO
zssget.egg-info/SOURCES.txt
zssget.egg-info/dependency_links.txt
zssget.egg-info/entry_points.txt
zssget.egg-info/requires.txt
zssget.egg-info/top_level.txt
zssget/util/__init__.py
zssget/util/log.py